median_circuit/Median_Circuit.v
module Median_Circuit(a2,a1,a0,R);

input   [7:0] a2,a1,a0;
output  [7:0] R;
wire    [7:0] R1,R2,R3;

assign R1=(a2>a1)?a2:a1;
assign R2=(a2>a0)?a2:a0;
assign R3=(a1>a0)?a1:a0;
assign R=(R1==R2)?R3:(R1==R3)?R2:(R2==R3)?R1:0;

endmodule

median_circuit/testbench_Median_Circuit.v
`include "Median_Circuit.v"

module testbench_Median_Circuit;
reg     [7:0] a0,a1,a2;

wire    [7:0] R;

Median_Circuit  R1(a0,a1,a2,R);

initial begin:testbench_Median_Circuit
integer i,j,k;
    for(i=1 ; i<129 ; i=i*2)
        begin
            a0=i;
            for(j=1 ; j<129 ; j=j*2)
                begin
                    a1=j;
                    for(k=1 ; k<129 ; k=k*2)
                        begin
                            a2=k;                            
                                        #10;
                                        
                        end
                end
        end
    $finish;
end

initial begin
$dumpfile("wave_Median_Circuit.vcd");
$dumpvars;
end

    initial $monitor("a0=%b a1=%b a2=%b R=%b", a0, a1, a2, R);
    
endmodule

median_circuit/MCD.vcd
$date
    May 16, 2020  18:13:42
$end
$version
    TOOL:	ncsim	15.20-s039
$end
$timescale
    1 ns
$end

$scope module testbench_Median_Circuit $end
$var reg       8 !    a0 [7:0] $end
$var reg       8 "    a1 [7:0] $end
$var reg       8 #    a2 [7:0] $end
$var wire      8 $    R [7:0] $end

$scope module R1 $end
$var wire      8 %    a2 [7:0] $end
$var wire      8 &    a1 [7:0] $end
$var wire      8 '    a0 [7:0] $end
$var wire      8 $    R [7:0] $end
$var wire      8 (    R1 [7:0] $end
$var wire      8 )    R2 [7:0] $end
$var wire      8 *    R3 [7:0] $end
$upscope $end


$scope begin testbench_Median_Circuit $end
$var integer  32 +    i  $end
$var integer  32 ,    j  $end
$var integer  32 -    k  $end
$upscope $end

$upscope $end

$enddefinitions $end
$dumpvars
b1 !
b1 "
b1 #
b1 $
b1 %
b1 &
b1 '
b1 (
b1 )
b1 *
b1 +
b1 ,
b1 -
$end
#10
b10 -
b10 #
b10 '
b10 )
b10 *
#20
b100 -
b100 #
b100 '
b100 )
b100 *
#30
b1000 -
b1000 #
b1000 '
b1000 )
b1000 *
#40
b10000 -
b10000 #
b10000 '
b10000 )
b10000 *
#50
b100000 -
b100000 #
b100000 '
b100000 )
b100000 *
#60
b1000000 -
b1000000 #
b1000000 '
b1000000 )
b1000000 *
#70
b10000000 -
b10000000 #
b10000000 '
b10000000 )
b10000000 *
#80
b100000000 -
b10 ,
b10 "
b1 -
b1 #
b1 '
b10 &
b10 (
b1 )
b10 *
#90
b10 -
b10 #
b10 '
b10 )
b10 $
#100
b100 -
b100 #
b100 '
b100 )
b100 *
#110
b1000 -
b1000 #
b1000 '
b1000 )
b1000 *
#120
b10000 -
b10000 #
b10000 '
b10000 )
b10000 *
#130
b100000 -
b100000 #
b100000 '
b100000 )
b100000 *
#140
b1000000 -
b1000000 #
b1000000 '
b1000000 )
b1000000 *
#150
b10000000 -
b10000000 #
b10000000 '
b10000000 )
b10000000 *
#160
b100000000 -
b100 ,
b100 "
b1 -
b1 #
b1 '
b100 &
b100 (
b1 )
b100 *
b1 $
#170
b10 -
b10 #
b10 '
b10 )
b10 $
#180
b100 -
b100 #
b100 '
b100 )
b100 $
#190
b1000 -
b1000 #
b1000 '
b1000 )
b1000 *
#200
b10000 -
b10000 #
b10000 '
b10000 )
b10000 *
#210
b100000 -
b100000 #
b100000 '
b100000 )
b100000 *
#220
b1000000 -
b1000000 #
b1000000 '
b1000000 )
b1000000 *
#230
b10000000 -
b10000000 #
b10000000 '
b10000000 )
b10000000 *
#240
b100000000 -
b1000 ,
b1000 "
b1 -
b1 #
b1 '
b1000 &
b1000 (
b1 )
b1000 *
b1 $
#250
b10 -
b10 #
b10 '
b10 )
b10 $
#260
b100 -
b100 #
b100 '
b100 )
b100 $
#270
b1000 -
b1000 #
b1000 '
b1000 )
b1000 $
#280
b10000 -
b10000 #
b10000 '
b10000 )
b10000 *
#290
b100000 -
b100000 #
b100000 '
b100000 )
b100000 *
#300
b1000000 -
b1000000 #
b1000000 '
b1000000 )
b1000000 *
#310
b10000000 -
b10000000 #
b10000000 '
b10000000 )
b10000000 *
#320
b100000000 -
b10000 ,
b10000 "
b1 -
b1 #
b1 '
b10000 &
b10000 (
b1 )
b10000 *
b1 $
#330
b10 -
b10 #
b10 '
b10 )
b10 $
#340
b100 -
b100 #
b100 '
b100 )
b100 $
#350
b1000 -
b1000 #
b1000 '
b1000 )
b1000 $
#360
b10000 -
b10000 #
b10000 '
b10000 )
b10000 $
#370
b100000 -
b100000 #
b100000 '
b100000 )
b100000 *
#380
b1000000 -
b1000000 #
b1000000 '
b1000000 )
b1000000 *
#390
b10000000 -
b10000000 #
b10000000 '
b10000000 )
b10000000 *
#400
b100000000 -
b100000 ,
b100000 "
b1 -
b1 #
b1 '
b100000 &
b100000 (
b1 )
b100000 *
b1 $
#410
b10 -
b10 #
b10 '
b10 )
b10 $
#420
b100 -
b100 #
b100 '
b100 )
b100 $
#430
b1000 -
b1000 #
b1000 '
b1000 )
b1000 $
#440
b10000 -
b10000 #
b10000 '
b10000 )
b10000 $
#450
b100000 -
b100000 #
b100000 '
b100000 )
b100000 $
#460
b1000000 -
b1000000 #
b1000000 '
b1000000 )
b1000000 *
#470
b10000000 -
b10000000 #
b10000000 '
b10000000 )
b10000000 *
#480
b100000000 -
b1000000 ,
b1000000 "
b1 -
b1 #
b1 '
b1000000 &
b1000000 (
b1 )
b1000000 *
b1 $
#490
b10 -
b10 #
b10 '
b10 )
b10 $
#500
b100 -
b100 #
b100 '
b100 )
b100 $
#510
b1000 -
b1000 #
b1000 '
b1000 )
b1000 $
#520
b10000 -
b10000 #
b10000 '
b10000 )
b10000 $
#530
b100000 -
b100000 #
b100000 '
b100000 )
b100000 $
#540
b1000000 -
b1000000 #
b1000000 '
b1000000 )
b1000000 $
#550
b10000000 -
b10000000 #
b10000000 '
b10000000 )
b10000000 *
#560
b100000000 -
b10000000 ,
b10000000 "
b1 -
b1 #
b1 '
b10000000 &
b10000000 (
b1 )
b1 $
#570
b10 -
b10 #
b10 '
b10 )
b10 $
#580
b100 -
b100 #
b100 '
b100 )
b100 $
#590
b1000 -
b1000 #
b1000 '
b1000 )
b1000 $
#600
b10000 -
b10000 #
b10000 '
b10000 )
b10000 $
#610
b100000 -
b100000 #
b100000 '
b100000 )
b100000 $
#620
b1000000 -
b1000000 #
b1000000 '
b1000000 )
b1000000 $
#630
b10000000 -
b10000000 #
b10000000 '
b10000000 )
b10000000 $
#640
b100000000 -
b100000000 ,
b10 +
b10 !
b1 ,
b1 "
b1 -
b1 #
b1 '
b1 &
b10 %
b10 (
b10 )
b1 *
b1 $
#650
b10 -
b10 #
b10 '
b10 *
b10 $
#660
b100 -
b100 #
b100 '
b100 )
b100 *
#670
b1000 -
b1000 #
b1000 '
b1000 )
b1000 *
#680
b10000 -
b10000 #
b10000 '
b10000 )
b10000 *
#690
b100000 -
b100000 #
b100000 '
b100000 )
b100000 *
#700
b1000000 -
b1000000 #
b1000000 '
b1000000 )
b1000000 *
#710
b10000000 -
b10000000 #
b10000000 '
b10000000 )
b10000000 *
#720
b100000000 -
b10 ,
b10 "
b1 -
b1 #
b1 '
b10 &
b10 )
b10 *
#730
b10 -
b10 #
b10 '
#740
b100 -
b100 #
b100 '
b100 )
b100 *
#750
b1000 -
b1000 #
b1000 '
b1000 )
b1000 *
#760
b10000 -
b10000 #
b10000 '
b10000 )
b10000 *
#770
b100000 -
b100000 #
b100000 '
b100000 )
b100000 *
#780
b1000000 -
b1000000 #
b1000000 '
b1000000 )
b1000000 *
#790
b10000000 -
b10000000 #
b10000000 '
b10000000 )
b10000000 *
#800
b100000000 -
b100 ,
b100 "
b1 -
b1 #
b1 '
b100 &
b100 (
b10 )
b100 *
#810
b10 -
b10 #
b10 '
#820
b100 -
b100 #
b100 '
b100 )
b100 $
#830
b1000 -
b1000 #
b1000 '
b1000 )
b1000 *
#840
b10000 -
b10000 #
b10000 '
b10000 )
b10000 *
#850
b100000 -
b100000 #
b100000 '
b100000 )
b100000 *
#860
b1000000 -
b1000000 #
b1000000 '
b1000000 )
b1000000 *
#870
b10000000 -
b10000000 #
b10000000 '
b10000000 )
b10000000 *
#880
b100000000 -
b1000 ,
b1000 "
b1 -
b1 #
b1 '
b1000 &
b1000 (
b10 )
b1000 *
b10 $
#890
b10 -
b10 #
b10 '
#900
b100 -
b100 #
b100 '
b100 )
b100 $
#910
b1000 -
b1000 #
b1000 '
b1000 )
b1000 $
#920
b10000 -
b10000 #
b10000 '
b10000 )
b10000 *
#930
b100000 -
b100000 #
b100000 '
b100000 )
b100000 *
#940
b1000000 -
b1000000 #
b1000000 '
b1000000 )
b1000000 *
#950
b10000000 -
b10000000 #
b10000000 '
b10000000 )
b10000000 *
#960
b100000000 -
b10000 ,
b10000 "
b1 -
b1 #
b1 '
b10000 &
b10000 (
b10 )
b10000 *
b10 $
#970
b10 -
b10 #
b10 '
#980
b100 -
b100 #
b100 '
b100 )
b100 $
#990
b1000 -
b1000 #
b1000 '
b1000 )
b1000 $
#1000
b10000 -
b10000 #
b10000 '
b10000 )
b10000 $
#1010
b100000 -
b100000 #
b100000 '
b100000 )
b100000 *
#1020
b1000000 -
b1000000 #
b1000000 '
b1000000 )
b1000000 *
#1030
b10000000 -
b10000000 #
b10000000 '
b10000000 )
b10000000 *
#1040
b100000000 -
b100000 ,
b100000 "
b1 -
b1 #
b1 '
b100000 &
b100000 (
b10 )
b100000 *
b10 $
#1050
b10 -
b10 #
b10 '
#1060
b100 -
b100 #
b100 '
b100 )
b100 $
#1070
b1000 -
b1000 #
b1000 '
b1000 )
b1000 $
#1080
b10000 -
b10000 #
b10000 '
b10000 )
b10000 $
#1090
b100000 -
b100000 #
b100000 '
b100000 )
b100000 $
#1100
b1000000 -
b1000000 #
b1000000 '
b1000000 )
b1000000 *
#1110
b10000000 -
b10000000 #
b10000000 '
b10000000 )
b10000000 *
#1120
b100000000 -
b1000000 ,
b1000000 "
b1 -
b1 #
b1 '
b1000000 &
b1000000 (
b10 )
b1000000 *
b10 $
#1130
b10 -
b10 #
b10 '
#1140
b100 -
b100 #
b100 '
b100 )
b100 $
#1150
b1000 -
b1000 #
b1000 '
b1000 )
b1000 $
#1160
b10000 -
b10000 #
b10000 '
b10000 )
b10000 $
#1170
b100000 -
b100000 #
b100000 '
b100000 )
b100000 $
#1180
b1000000 -
b1000000 #
b1000000 '
b1000000 )
b1000000 $
#1190
b10000000 -
b10000000 #
b10000000 '
b10000000 )
b10000000 *
#1200
b100000000 -
b10000000 ,
b10000000 "
b1 -
b1 #
b1 '
b10000000 &
b10000000 (
b10 )
b10 $
#1210
b10 -
b10 #
b10 '
#1220
b100 -
b100 #
b100 '
b100 )
b100 $
#1230
b1000 -
b1000 #
b1000 '
b1000 )
b1000 $
#1240
b10000 -
b10000 #
b10000 '
b10000 )
b10000 $
#1250
b100000 -
b100000 #
b100000 '
b100000 )
b100000 $
#1260
b1000000 -
b1000000 #
b1000000 '
b1000000 )
b1000000 $
#1270
b10000000 -
b10000000 #
b10000000 '
b10000000 )
b10000000 $
#1280
b100000000 -
b100000000 ,
b100 +
b100 !
b1 ,
b1 "
b1 -
b1 #
b1 '
b1 &
b100 %
b100 (
b100 )
b1 *
b1 $
#1290
b10 -
b10 #
b10 '
b10 *
b10 $
#1300
b100 -
b100 #
b100 '
b100 *
b100 $
#1310
b1000 -
b1000 #
b1000 '
b1000 )
b1000 *
#1320
b10000 -
b10000 #
b10000 '
b10000 )
b10000 *
#1330
b100000 -
b100000 #
b100000 '
b100000 )
b100000 *
#1340
b1000000 -
b1000000 #
b1000000 '
b1000000 )
b1000000 *
#1350
b10000000 -
b10000000 #
b10000000 '
b10000000 )
b10000000 *
#1360
b100000000 -
b10 ,
b10 "
b1 -
b1 #
b1 '
b10 &
b100 )
b10 *
b10 $
#1370
b10 -
b10 #
b10 '
#1380
b100 -
b100 #
b100 '
b100 *
b100 $
#1390
b1000 -
b1000 #
b1000 '
b1000 )
b1000 *
#1400
b10000 -
b10000 #
b10000 '
b10000 )
b10000 *
#1410
b100000 -
b100000 #
b100000 '
b100000 )
b100000 *
#1420
b1000000 -
b1000000 #
b1000000 '
b1000000 )
b1000000 *
#1430
b10000000 -
b10000000 #
b10000000 '
b10000000 )
b10000000 *
#1440
b100000000 -
b100 ,
b100 "
b1 -
b1 #
b1 '
b100 &
b100 )
b100 *
#1450
b10 -
b10 #
b10 '
#1460
b100 -
b100 #
b100 '
#1470
b1000 -
b1000 #
b1000 '
b1000 )
b1000 *
#1480
b10000 -
b10000 #
b10000 '
b10000 )
b10000 *
#1490
b100000 -
b100000 #
b100000 '
b100000 )
b100000 *
#1500
b1000000 -
b1000000 #
b1000000 '
b1000000 )
b1000000 *
#1510
b10000000 -
b10000000 #
b10000000 '
b10000000 )
b10000000 *
#1520
b100000000 -
b1000 ,
b1000 "
b1 -
b1 #
b1 '
b1000 &
b1000 (
b100 )
b1000 *
#1530
b10 -
b10 #
b10 '
#1540
b100 -
b100 #
b100 '
#1550
b1000 -
b1000 #
b1000 '
b1000 )
b1000 $
#1560
b10000 -
b10000 #
b10000 '
b10000 )
b10000 *
#1570
b100000 -
b100000 #
b100000 '
b100000 )
b100000 *
#1580
b1000000 -
b1000000 #
b1000000 '
b1000000 )
b1000000 *
#1590
b10000000 -
b10000000 #
b10000000 '
b10000000 )
b10000000 *
#1600
b100000000 -
b10000 ,
b10000 "
b1 -
b1 #
b1 '
b10000 &
b10000 (
b100 )
b10000 *
b100 $
#1610
b10 -
b10 #
b10 '
#1620
b100 -
b100 #
b100 '
#1630
b1000 -
b1000 #
b1000 '
b1000 )
b1000 $
#1640
b10000 -
b10000 #
b10000 '
b10000 )
b10000 $
#1650
b100000 -
b100000 #
b100000 '
b100000 )
b100000 *
#1660
b1000000 -
b1000000 #
b1000000 '
b1000000 )
b1000000 *
#1670
b10000000 -
b10000000 #
b10000000 '
b10000000 )
b10000000 *
#1680
b100000000 -
b100000 ,
b100000 "
b1 -
b1 #
b1 '
b100000 &
b100000 (
b100 )
b100000 *
b100 $
#1690
b10 -
b10 #
b10 '
#1700
b100 -
b100 #
b100 '
#1710
b1000 -
b1000 #
b1000 '
b1000 )
b1000 $
#1720
b10000 -
b10000 #
b10000 '
b10000 )
b10000 $
#1730
b100000 -
b100000 #
b100000 '
b100000 )
b100000 $
#1740
b1000000 -
b1000000 #
b1000000 '
b1000000 )
b1000000 *
#1750
b10000000 -
b10000000 #
b10000000 '
b10000000 )
b10000000 *
#1760
b100000000 -
b1000000 ,
b1000000 "
b1 -
b1 #
b1 '
b1000000 &
b1000000 (
b100 )
b1000000 *
b100 $
#1770
b10 -
b10 #
b10 '
#1780
b100 -
b100 #
b100 '
#1790
b1000 -
b1000 #
b1000 '
b1000 )
b1000 $
#1800
b10000 -
b10000 #
b10000 '
b10000 )
b10000 $
#1810
b100000 -
b100000 #
b100000 '
b100000 )
b100000 $
#1820
b1000000 -
b1000000 #
b1000000 '
b1000000 )
b1000000 $
#1830
b10000000 -
b10000000 #
b10000000 '
b10000000 )
b10000000 *
#1840
b100000000 -
b10000000 ,
b10000000 "
b1 -
b1 #
b1 '
b10000000 &
b10000000 (
b100 )
b100 $
#1850
b10 -
b10 #
b10 '
#1860
b100 -
b100 #
b100 '
#1870
b1000 -
b1000 #
b1000 '
b1000 )
b1000 $
#1880
b10000 -
b10000 #
b10000 '
b10000 )
b10000 $
#1890
b100000 -
b100000 #
b100000 '
b100000 )
b100000 $
#1900
b1000000 -
b1000000 #
b1000000 '
b1000000 )
b1000000 $
#1910
b10000000 -
b10000000 #
b10000000 '
b10000000 )
b10000000 $
#1920
b100000000 -
b100000000 ,
b1000 +
b1000 !
b1 ,
b1 "
b1 -
b1 #
b1 '
b1 &
b1000 %
b1000 (
b1000 )
b1 *
b1 $
#1930
b10 -
b10 #
b10 '
b10 *
b10 $
#1940
b100 -
b100 #
b100 '
b100 *
b100 $
#1950
b1000 -
b1000 #
b1000 '
b1000 *
b1000 $
#1960
b10000 -
b10000 #
b10000 '
b10000 )
b10000 *
#1970
b100000 -
b100000 #
b100000 '
b100000 )
b100000 *
#1980
b1000000 -
b1000000 #
b1000000 '
b1000000 )
b1000000 *
#1990
b10000000 -
b10000000 #
b10000000 '
b10000000 )
b10000000 *
#2000
b100000000 -
b10 ,
b10 "
b1 -
b1 #
b1 '
b10 &
b1000 )
b10 *
b10 $
#2010
b10 -
b10 #
b10 '
#2020
b100 -
b100 #
b100 '
b100 *
b100 $
#2030
b1000 -
b1000 #
b1000 '
b1000 *
b1000 $
#2040
b10000 -
b10000 #
b10000 '
b10000 )
b10000 *
#2050
b100000 -
b100000 #
b100000 '
b100000 )
b100000 *
#2060
b1000000 -
b1000000 #
b1000000 '
b1000000 )
b1000000 *
#2070
b10000000 -
b10000000 #
b10000000 '
b10000000 )
b10000000 *
#2080
b100000000 -
b100 ,
b100 "
b1 -
b1 #
b1 '
b100 &
b1000 )
b100 *
b100 $
#2090
b10 -
b10 #
b10 '
#2100
b100 -
b100 #
b100 '
#2110
b1000 -
b1000 #
b1000 '
b1000 *
b1000 $
#2120
b10000 -
b10000 #
b10000 '
b10000 )
b10000 *
#2130
b100000 -
b100000 #
b100000 '
b100000 )
b100000 *
#2140
b1000000 -
b1000000 #
b1000000 '
b1000000 )
b1000000 *
#2150
b10000000 -
b10000000 #
b10000000 '
b10000000 )
b10000000 *
#2160
b100000000 -
b1000 ,
b1000 "
b1 -
b1 #
b1 '
b1000 &
b1000 )
b1000 *
#2170
b10 -
b10 #
b10 '
#2180
b100 -
b100 #
b100 '
#2190
b1000 -
b1000 #
b1000 '
#2200
b10000 -
b10000 #
b10000 '
b10000 )
b10000 *
#2210
b100000 -
b100000 #
b100000 '
b100000 )
b100000 *
#2220
b1000000 -
b1000000 #
b1000000 '
b1000000 )
b1000000 *
#2230
b10000000 -
b10000000 #
b10000000 '
b10000000 )
b10000000 *
#2240
b100000000 -
b10000 ,
b10000 "
b1 -
b1 #
b1 '
b10000 &
b10000 (
b1000 )
b10000 *
#2250
b10 -
b10 #
b10 '
#2260
b100 -
b100 #
b100 '
#2270
b1000 -
b1000 #
b1000 '
#2280
b10000 -
b10000 #
b10000 '
b10000 )
b10000 $
#2290
b100000 -
b100000 #
b100000 '
b100000 )
b100000 *
#2300
b1000000 -
b1000000 #
b1000000 '
b1000000 )
b1000000 *
#2310
b10000000 -
b10000000 #
b10000000 '
b10000000 )
b10000000 *
#2320
b100000000 -
b100000 ,
b100000 "
b1 -
b1 #
b1 '
b100000 &
b100000 (
b1000 )
b100000 *
b1000 $
#2330
b10 -
b10 #
b10 '
#2340
b100 -
b100 #
b100 '
#2350
b1000 -
b1000 #
b1000 '
#2360
b10000 -
b10000 #
b10000 '
b10000 )
b10000 $
#2370
b100000 -
b100000 #
b100000 '
b100000 )
b100000 $
#2380
b1000000 -
b1000000 #
b1000000 '
b1000000 )
b1000000 *
#2390
b10000000 -
b10000000 #
b10000000 '
b10000000 )
b10000000 *
#2400
b100000000 -
b1000000 ,
b1000000 "
b1 -
b1 #
b1 '
b1000000 &
b1000000 (
b1000 )
b1000000 *
b1000 $
#2410
b10 -
b10 #
b10 '
#2420
b100 -
b100 #
b100 '
#2430
b1000 -
b1000 #
b1000 '
#2440
b10000 -
b10000 #
b10000 '
b10000 )
b10000 $
#2450
b100000 -
b100000 #
b100000 '
b100000 )
b100000 $
#2460
b1000000 -
b1000000 #
b1000000 '
b1000000 )
b1000000 $
#2470
b10000000 -
b10000000 #
b10000000 '
b10000000 )
b10000000 *
#2480
b100000000 -
b10000000 ,
b10000000 "
b1 -
b1 #
b1 '
b10000000 &
b10000000 (
b1000 )
b1000 $
#2490
b10 -
b10 #
b10 '
#2500
b100 -
b100 #
b100 '
#2510
b1000 -
b1000 #
b1000 '
#2520
b10000 -
b10000 #
b10000 '
b10000 )
b10000 $
#2530
b100000 -
b100000 #
b100000 '
b100000 )
b100000 $
#2540
b1000000 -
b1000000 #
b1000000 '
b1000000 )
b1000000 $
#2550
b10000000 -
b10000000 #
b10000000 '
b10000000 )
b10000000 $
#2560
b100000000 -
b100000000 ,
b10000 +
b10000 !
b1 ,
b1 "
b1 -
b1 #
b1 '
b1 &
b10000 %
b10000 (
b10000 )
b1 *
b1 $
#2570
b10 -
b10 #
b10 '
b10 *
b10 $
#2580
b100 -
b100 #
b100 '
b100 *
b100 $
#2590
b1000 -
b1000 #
b1000 '
b1000 *
b1000 $
#2600
b10000 -
b10000 #
b10000 '
b10000 *
b10000 $
#2610
b100000 -
b100000 #
b100000 '
b100000 )
b100000 *
#2620
b1000000 -
b1000000 #
b1000000 '
b1000000 )
b1000000 *
#2630
b10000000 -
b10000000 #
b10000000 '
b10000000 )
b10000000 *
#2640
b100000000 -
b10 ,
b10 "
b1 -
b1 #
b1 '
b10 &
b10000 )
b10 *
b10 $
#2650
b10 -
b10 #
b10 '
#2660
b100 -
b100 #
b100 '
b100 *
b100 $
#2670
b1000 -
b1000 #
b1000 '
b1000 *
b1000 $
#2680
b10000 -
b10000 #
b10000 '
b10000 *
b10000 $
#2690
b100000 -
b100000 #
b100000 '
b100000 )
b100000 *
#2700
b1000000 -
b1000000 #
b1000000 '
b1000000 )
b1000000 *
#2710
b10000000 -
b10000000 #
b10000000 '
b10000000 )
b10000000 *
#2720
b100000000 -
b100 ,
b100 "
b1 -
b1 #
b1 '
b100 &
b10000 )
b100 *
b100 $
#2730
b10 -
b10 #
b10 '
#2740
b100 -
b100 #
b100 '
#2750
b1000 -
b1000 #
b1000 '
b1000 *
b1000 $
#2760
b10000 -
b10000 #
b10000 '
b10000 *
b10000 $
#2770
b100000 -
b100000 #
b100000 '
b100000 )
b100000 *
#2780
b1000000 -
b1000000 #
b1000000 '
b1000000 )
b1000000 *
#2790
b10000000 -
b10000000 #
b10000000 '
b10000000 )
b10000000 *
#2800
b100000000 -
b1000 ,
b1000 "
b1 -
b1 #
b1 '
b1000 &
b10000 )
b1000 *
b1000 $
#2810
b10 -
b10 #
b10 '
#2820
b100 -
b100 #
b100 '
#2830
b1000 -
b1000 #
b1000 '
#2840
b10000 -
b10000 #
b10000 '
b10000 *
b10000 $
#2850
b100000 -
b100000 #
b100000 '
b100000 )
b100000 *
#2860
b1000000 -
b1000000 #
b1000000 '
b1000000 )
b1000000 *
#2870
b10000000 -
b10000000 #
b10000000 '
b10000000 )
b10000000 *
#2880
b100000000 -
b10000 ,
b10000 "
b1 -
b1 #
b1 '
b10000 &
b10000 )
b10000 *
#2890
b10 -
b10 #
b10 '
#2900
b100 -
b100 #
b100 '
#2910
b1000 -
b1000 #
b1000 '
#2920
b10000 -
b10000 #
b10000 '
#2930
b100000 -
b100000 #
b100000 '
b100000 )
b100000 *
#2940
b1000000 -
b1000000 #
b1000000 '
b1000000 )
b1000000 *
#2950
b10000000 -
b10000000 #
b10000000 '
b10000000 )
b10000000 *
#2960
b100000000 -
b100000 ,
b100000 "
b1 -
b1 #
b1 '
b100000 &
b100000 (
b10000 )
b100000 *
#2970
b10 -
b10 #
b10 '
#2980
b100 -
b100 #
b100 '
#2990
b1000 -
b1000 #
b1000 '
#3000
b10000 -
b10000 #
b10000 '
#3010
b100000 -
b100000 #
b100000 '
b100000 )
b100000 $
#3020
b1000000 -
b1000000 #
b1000000 '
b1000000 )
b1000000 *
#3030
b10000000 -
b10000000 #
b10000000 '
b10000000 )
b10000000 *
#3040
b100000000 -
b1000000 ,
b1000000 "
b1 -
b1 #
b1 '
b1000000 &
b1000000 (
b10000 )
b1000000 *
b10000 $
#3050
b10 -
b10 #
b10 '
#3060
b100 -
b100 #
b100 '
#3070
b1000 -
b1000 #
b1000 '
#3080
b10000 -
b10000 #
b10000 '
#3090
b100000 -
b100000 #
b100000 '
b100000 )
b100000 $
#3100
b1000000 -
b1000000 #
b1000000 '
b1000000 )
b1000000 $
#3110
b10000000 -
b10000000 #
b10000000 '
b10000000 )
b10000000 *
#3120
b100000000 -
b10000000 ,
b10000000 "
b1 -
b1 #
b1 '
b10000000 &
b10000000 (
b10000 )
b10000 $
#3130
b10 -
b10 #
b10 '
#3140
b100 -
b100 #
b100 '
#3150
b1000 -
b1000 #
b1000 '
#3160
b10000 -
b10000 #
b10000 '
#3170
b100000 -
b100000 #
b100000 '
b100000 )
b100000 $
#3180
b1000000 -
b1000000 #
b1000000 '
b1000000 )
b1000000 $
#3190
b10000000 -
b10000000 #
b10000000 '
b10000000 )
b10000000 $
#3200
b100000000 -
b100000000 ,
b100000 +
b100000 !
b1 ,
b1 "
b1 -
b1 #
b1 '
b1 &
b100000 %
b100000 (
b100000 )
b1 *
b1 $
#3210
b10 -
b10 #
b10 '
b10 *
b10 $
#3220
b100 -
b100 #
b100 '
b100 *
b100 $
#3230
b1000 -
b1000 #
b1000 '
b1000 *
b1000 $
#3240
b10000 -
b10000 #
b10000 '
b10000 *
b10000 $
#3250
b100000 -
b100000 #
b100000 '
b100000 *
b100000 $
#3260
b1000000 -
b1000000 #
b1000000 '
b1000000 )
b1000000 *
#3270
b10000000 -
b10000000 #
b10000000 '
b10000000 )
b10000000 *
#3280
b100000000 -
b10 ,
b10 "
b1 -
b1 #
b1 '
b10 &
b100000 )
b10 *
b10 $
#3290
b10 -
b10 #
b10 '
#3300
b100 -
b100 #
b100 '
b100 *
b100 $
#3310
b1000 -
b1000 #
b1000 '
b1000 *
b1000 $
#3320
b10000 -
b10000 #
b10000 '
b10000 *
b10000 $
#3330
b100000 -
b100000 #
b100000 '
b100000 *
b100000 $
#3340
b1000000 -
b1000000 #
b1000000 '
b1000000 )
b1000000 *
#3350
b10000000 -
b10000000 #
b10000000 '
b10000000 )
b10000000 *
#3360
b100000000 -
b100 ,
b100 "
b1 -
b1 #
b1 '
b100 &
b100000 )
b100 *
b100 $
#3370
b10 -
b10 #
b10 '
#3380
b100 -
b100 #
b100 '
#3390
b1000 -
b1000 #
b1000 '
b1000 *
b1000 $
#3400
b10000 -
b10000 #
b10000 '
b10000 *
b10000 $
#3410
b100000 -
b100000 #
b100000 '
b100000 *
b100000 $
#3420
b1000000 -
b1000000 #
b1000000 '
b1000000 )
b1000000 *
#3430
b10000000 -
b10000000 #
b10000000 '
b10000000 )
b10000000 *
#3440
b100000000 -
b1000 ,
b1000 "
b1 -
b1 #
b1 '
b1000 &
b100000 )
b1000 *
b1000 $
#3450
b10 -
b10 #
b10 '
#3460
b100 -
b100 #
b100 '
#3470
b1000 -
b1000 #
b1000 '
#3480
b10000 -
b10000 #
b10000 '
b10000 *
b10000 $
#3490
b100000 -
b100000 #
b100000 '
b100000 *
b100000 $
#3500
b1000000 -
b1000000 #
b1000000 '
b1000000 )
b1000000 *
#3510
b10000000 -
b10000000 #
b10000000 '
b10000000 )
b10000000 *
#3520
b100000000 -
b10000 ,
b10000 "
b1 -
b1 #
b1 '
b10000 &
b100000 )
b10000 *
b10000 $
#3530
b10 -
b10 #
b10 '
#3540
b100 -
b100 #
b100 '
#3550
b1000 -
b1000 #
b1000 '
#3560
b10000 -
b10000 #
b10000 '
#3570
b100000 -
b100000 #
b100000 '
b100000 *
b100000 $
#3580
b1000000 -
b1000000 #
b1000000 '
b1000000 )
b1000000 *
#3590
b10000000 -
b10000000 #
b10000000 '
b10000000 )
b10000000 *
#3600
b100000000 -
b100000 ,
b100000 "
b1 -
b1 #
b1 '
b100000 &
b100000 )
b100000 *
#3610
b10 -
b10 #
b10 '
#3620
b100 -
b100 #
b100 '
#3630
b1000 -
b1000 #
b1000 '
#3640
b10000 -
b10000 #
b10000 '
#3650
b100000 -
b100000 #
b100000 '
#3660
b1000000 -
b1000000 #
b1000000 '
b1000000 )
b1000000 *
#3670
b10000000 -
b10000000 #
b10000000 '
b10000000 )
b10000000 *
#3680
b100000000 -
b1000000 ,
b1000000 "
b1 -
b1 #
b1 '
b1000000 &
b1000000 (
b100000 )
b1000000 *
#3690
b10 -
b10 #
b10 '
#3700
b100 -
b100 #
b100 '
#3710
b1000 -
b1000 #
b1000 '
#3720
b10000 -
b10000 #
b10000 '
#3730
b100000 -
b100000 #
b100000 '
#3740
b1000000 -
b1000000 #
b1000000 '
b1000000 )
b1000000 $
#3750
b10000000 -
b10000000 #
b10000000 '
b10000000 )
b10000000 *
#3760
b100000000 -
b10000000 ,
b10000000 "
b1 -
b1 #
b1 '
b10000000 &
b10000000 (
b100000 )
b100000 $
#3770
b10 -
b10 #
b10 '
#3780
b100 -
b100 #
b100 '
#3790
b1000 -
b1000 #
b1000 '
#3800
b10000 -
b10000 #
b10000 '
#3810
b100000 -
b100000 #
b100000 '
#3820
b1000000 -
b1000000 #
b1000000 '
b1000000 )
b1000000 $
#3830
b10000000 -
b10000000 #
b10000000 '
b10000000 )
b10000000 $
#3840
b100000000 -
b100000000 ,
b1000000 +
b1000000 !
b1 ,
b1 "
b1 -
b1 #
b1 '
b1 &
b1000000 %
b1000000 (
b1000000 )
b1 *
b1 $
#3850
b10 -
b10 #
b10 '
b10 *
b10 $
#3860
b100 -
b100 #
b100 '
b100 *
b100 $
#3870
b1000 -
b1000 #
b1000 '
b1000 *
b1000 $
#3880
b10000 -
b10000 #
b10000 '
b10000 *
b10000 $
#3890
b100000 -
b100000 #
b100000 '
b100000 *
b100000 $
#3900
b1000000 -
b1000000 #
b1000000 '
b1000000 *
b1000000 $
#3910
b10000000 -
b10000000 #
b10000000 '
b10000000 )
b10000000 *
#3920
b100000000 -
b10 ,
b10 "
b1 -
b1 #
b1 '
b10 &
b1000000 )
b10 *
b10 $
#3930
b10 -
b10 #
b10 '
#3940
b100 -
b100 #
b100 '
b100 *
b100 $
