voting_circuit/Vote_machine.v
module Vote_machine(A,B,C,D,E,R);

input [2:0] A,B,C,D,E;
output[2:0] R;

wire    [2:0] M0,M1,M2,Rt;

assign M0=A[0]+B[0]+C[0]+D[0]+E[0];
assign M1=A[1]+B[1]+C[1]+D[1]+E[1];
assign M2=A[2]+B[2]+C[2]+D[2]+E[2];


assign Rt[0]=((M0>=M2)?((M0>=M1)?1:0):0);
assign Rt[1]=((M1>=M2)?((M1>=M0)?1:0):0);
assign Rt[2]=((M2>=M1)?((M2>=M0)?1:0):0);

assign R[2]=Rt[2];
assign R[1]=(~Rt[2])&Rt[1];
assign R[0]=(~Rt[2])&(~Rt[1])&Rt[0];

endmodule

voting_circuit/testbench_Vote_machine.v
`include "Vote_machine.v"

module testbench_Vote_machine;
reg     [2:0] A,B,C,D,E;

wire    [2:0] R;

Vote_machine R0(A,B,C,D,E,R);

initial begin:testbench_Vote_machine
integer i,j,k,l,m;
    for(i=1 ; i<5 ; i=i*2)
        begin
            A=i;
            for(j=1 ; j<5 ; j=j*2)
                begin
                    B=j;
                    for(k=1 ; k<5 ; k=k*2)
                        begin
                            C=k;
                            for(l=1 ; l<5 ; l=l*2)
                                begin
                                    D=l;
                                    for(m=1 ; m<5 ; m=m*2)
                                        begin
                                            E=m;
                            
                                        #10;
                            
                                        end
                                end
                        end
                end
        end
    $finish;
end

initial begin
$dumpfile("wave_Votemachine.vcd");
$dumpvars;
end

    initial $monitor("A=%b B=%b C=%b D=%b E=%b R=%b", A, B, C, D, E, R);
    
endmodule

voting_circuit/vote.vcd
$date
    May 16, 2020  18:11:12
$end
$version
    TOOL:	ncsim	15.20-s039
$end
$timescale
    1 ns
$end

$scope module testbench_Vote_machine $end
$var reg       3 !    A [2:0] $end
$var reg       3 "    B [2:0] $end
$var reg       3 #    C [2:0] $end
$var reg       3 $    D [2:0] $end
$var reg       3 %    E [2:0] $end
$var wire      3 &    R [2:0] $end

$scope module R0 $end
$var wire      3 '    A [2:0] $end
$var wire      3 (    B [2:0] $end
$var wire      3 )    C [2:0] $end
$var wire      3 *    D [2:0] $end
$var wire      3 +    E [2:0] $end
$var wire      3 &    R [2:0] $end
$var wire      3 ,    M0 [2:0] $end
$var wire      3 -    M1 [2:0] $end
$var wire      3 .    M2 [2:0] $end
$var wire      3 /    Rt [2:0] $end
$upscope $end


$scope begin testbench_Vote_machine $end
$var integer  32 0    i  $end
$var integer  32 1    j  $end
$var integer  32 2    k  $end
$var integer  32 3    l  $end
$var integer  32 4    m  $end
$upscope $end

$upscope $end

$enddefinitions $end
$dumpvars
b1 !
b1 "
b1 #
b1 $
b1 %
b1 &
b1 '
b1 (
b1 )
b1 *
b1 +
b101 ,
b0 -
b0 .
b1 /
b1 0
b1 1
b1 2
b1 3
b1 4
$end
#10
b10 4
b10 %
b10 +
b1 -
b100 ,
#20
b100 4
b100 %
b100 +
b1 .
b0 -
#30
b1000 4
b10 3
b10 $
b1 4
b1 %
b1 +
b10 *
b0 .
b1 -
#40
b10 4
b10 %
b10 +
b10 -
b11 ,
#50
b100 4
b100 %
b100 +
b1 .
b1 -
#60
b1000 4
b100 3
b100 $
b1 4
b1 %
b1 +
b100 *
b0 -
b100 ,
#70
b10 4
b10 %
b10 +
b1 -
b11 ,
#80
b100 4
b100 %
b100 +
b10 .
b0 -
#90
b1000 4
b1000 3
b10 2
b10 #
b1 3
b1 $
b1 4
b1 %
b1 +
b1 *
b10 )
b0 .
b1 -
b100 ,
#100
b10 4
b10 %
b10 +
b10 -
b11 ,
#110
b100 4
b100 %
b100 +
b1 .
b1 -
#120
b1000 4
b10 3
b10 $
b1 4
b1 %
b1 +
b10 *
b0 .
b10 -
#130
b10 4
b10 %
b10 +
b11 -
b10 ,
b10 /
b10 &
#140
b100 4
b100 %
b100 +
b1 .
b10 -
b11 /
#150
b1000 4
b100 3
b100 $
b1 4
b1 %
b1 +
b100 *
b1 -
b11 ,
b1 /
b1 &
#160
b10 4
b10 %
b10 +
b10 -
b10 ,
b11 /
b10 &
#170
b100 4
b100 %
b100 +
b10 .
b1 -
b101 /
b100 &
#180
b1000 4
b1000 3
b100 2
b100 #
b1 3
b1 $
b1 4
b1 %
b1 +
b1 *
b100 )
b1 .
b0 -
b100 ,
b1 /
b1 &
#190
b10 4
b10 %
b10 +
b1 -
b11 ,
#200
b100 4
b100 %
b100 +
b10 .
b0 -
#210
b1000 4
b10 3
b10 $
b1 4
b1 %
b1 +
b10 *
b1 .
b1 -
#220
b10 4
b10 %
b10 +
b10 -
b10 ,
b11 /
b10 &
#230
b100 4
b100 %
b100 +
b10 .
b1 -
b101 /
b100 &
#240
b1000 4
b100 3
b100 $
b1 4
b1 %
b1 +
b100 *
b0 -
b11 ,
b1 /
b1 &
#250
b10 4
b10 %
b10 +
b1 -
b10 ,
b101 /
b100 &
#260
b100 4
b100 %
b100 +
b11 .
b0 -
b100 /
#270
b1000 4
b1000 3
b1000 2
b10 1
b10 "
b1 2
b1 #
b1 3
b1 $
b1 4
b1 %
b1 +
b1 *
b1 )
b10 (
b0 .
b1 -
b100 ,
b1 /
b1 &
#280
b10 4
b10 %
b10 +
b10 -
b11 ,
#290
b100 4
b100 %
b100 +
b1 .
b1 -
#300
b1000 4
b10 3
b10 $
b1 4
b1 %
b1 +
b10 *
b0 .
b10 -
#310
b10 4
b10 %
b10 +
b11 -
b10 ,
b10 /
b10 &
#320
b100 4
b100 %
b100 +
b1 .
b10 -
b11 /
#330
b1000 4
b100 3
b100 $
b1 4
b1 %
b1 +
b100 *
b1 -
b11 ,
b1 /
b1 &
#340
b10 4
b10 %
b10 +
b10 -
b10 ,
b11 /
b10 &
#350
b100 4
b100 %
b100 +
b10 .
b1 -
b101 /
b100 &
#360
b1000 4
b1000 3
b10 2
b10 #
b1 3
b1 $
b1 4
b1 %
b1 +
b1 *
b10 )
b0 .
b10 -
b11 ,
b1 /
b1 &
#370
b10 4
b10 %
b10 +
b11 -
b10 ,
b10 /
b10 &
#380
b100 4
b100 %
b100 +
b1 .
b10 -
b11 /
#390
b1000 4
b10 3
b10 $
b1 4
b1 %
b1 +
b10 *
b0 .
b11 -
b10 /
#400
b10 4
b10 %
b10 +
b100 -
b1 ,
#410
b100 4
b100 %
b100 +
b1 .
b11 -
#420
b1000 4
b100 3
b100 $
b1 4
b1 %
b1 +
b100 *
b10 -
b10 ,
b11 /
#430
b10 4
b10 %
b10 +
b11 -
b1 ,
b10 /
#440
b100 4
b100 %
b100 +
b10 .
b10 -
b110 /
b100 &
#450
b1000 4
b1000 3
b100 2
b100 #
b1 3
b1 $
b1 4
b1 %
b1 +
b1 *
b100 )
b1 .
b1 -
b11 ,
b1 /
b1 &
#460
b10 4
b10 %
b10 +
b10 -
b10 ,
b11 /
b10 &
#470
b100 4
b100 %
b100 +
b10 .
b1 -
b101 /
b100 &
#480
b1000 4
b10 3
b10 $
b1 4
b1 %
b1 +
b10 *
b1 .
b10 -
b11 /
b10 &
#490
b10 4
b10 %
b10 +
b11 -
b1 ,
b10 /
#500
b100 4
b100 %
b100 +
b10 .
b10 -
b110 /
b100 &
#510
b1000 4
b100 3
b100 $
b1 4
b1 %
b1 +
b100 *
b1 -
b10 ,
b101 /
#520
b10 4
b10 %
b10 +
b10 -
b1 ,
b110 /
#530
b100 4
b100 %
b100 +
b11 .
b1 -
b100 /
#540
b1000 4
b1000 3
b1000 2
b100 1
b100 "
b1 2
b1 #
b1 3
b1 $
b1 4
b1 %
b1 +
b1 *
b1 )
b100 (
b1 .
b0 -
b100 ,
b1 /
b1 &
#550
b10 4
b10 %
b10 +
b1 -
b11 ,
#560
b100 4
b100 %
b100 +
b10 .
b0 -
#570
b1000 4
b10 3
b10 $
b1 4
b1 %
b1 +
b10 *
b1 .
b1 -
#580
b10 4
b10 %
b10 +
b10 -
b10 ,
b11 /
b10 &
#590
b100 4
b100 %
b100 +
b10 .
b1 -
b101 /
b100 &
#600
b1000 4
b100 3
b100 $
b1 4
b1 %
b1 +
b100 *
b0 -
b11 ,
b1 /
b1 &
#610
b10 4
b10 %
b10 +
b1 -
b10 ,
b101 /
b100 &
#620
b100 4
b100 %
b100 +
b11 .
b0 -
b100 /
#630
b1000 4
b1000 3
b10 2
b10 #
b1 3
b1 $
b1 4
b1 %
b1 +
b1 *
b10 )
b1 .
b1 -
b11 ,
b1 /
b1 &
#640
b10 4
b10 %
b10 +
b10 -
b10 ,
b11 /
b10 &
#650
b100 4
b100 %
b100 +
b10 .
b1 -
b101 /
b100 &
#660
b1000 4
b10 3
b10 $
b1 4
b1 %
b1 +
b10 *
b1 .
b10 -
b11 /
b10 &
#670
b10 4
b10 %
b10 +
b11 -
b1 ,
b10 /
#680
b100 4
b100 %
b100 +
b10 .
b10 -
b110 /
b100 &
#690
b1000 4
b100 3
b100 $
b1 4
b1 %
b1 +
b100 *
b1 -
b10 ,
b101 /
#700
b10 4
b10 %
b10 +
b10 -
b1 ,
b110 /
#710
b100 4
b100 %
b100 +
b11 .
b1 -
b100 /
#720
b1000 4
b1000 3
b100 2
b100 #
b1 3
b1 $
b1 4
b1 %
b1 +
b1 *
b100 )
b10 .
b0 -
b11 ,
b1 /
b1 &
#730
b10 4
b10 %
b10 +
b1 -
b10 ,
b101 /
b100 &
#740
b100 4
b100 %
b100 +
b11 .
b0 -
b100 /
#750
b1000 4
b10 3
b10 $
b1 4
b1 %
b1 +
b10 *
b10 .
b1 -
b101 /
#760
b10 4
b10 %
b10 +
b10 -
b1 ,
b110 /
#770
b100 4
b100 %
b100 +
b11 .
b1 -
b100 /
#780
b1000 4
b100 3
b100 $
b1 4
b1 %
b1 +
b100 *
b0 -
b10 ,
#790
b10 4
b10 %
b10 +
b1 -
b1 ,
#800
b100 4
b100 %
b100 +
b100 .
b0 -
#810
b1000 4
b1000 3
b1000 2
b1000 1
b10 0
b10 !
b1 1
b1 "
b1 2
b1 #
b1 3
b1 $
b1 4
b1 %
b1 +
b1 *
b1 )
b1 (
b10 '
b0 .
b1 -
b100 ,
b1 /
b1 &
#820
b10 4
b10 %
b10 +
b10 -
b11 ,
#830
b100 4
b100 %
b100 +
b1 .
b1 -
#840
b1000 4
b10 3
b10 $
b1 4
b1 %
b1 +
b10 *
b0 .
b10 -
#850
b10 4
b10 %
b10 +
b11 -
b10 ,
b10 /
b10 &
#860
b100 4
b100 %
b100 +
b1 .
b10 -
b11 /
#870
b1000 4
b100 3
b100 $
b1 4
b1 %
b1 +
b100 *
b1 -
b11 ,
b1 /
b1 &
#880
b10 4
b10 %
b10 +
b10 -
b10 ,
b11 /
b10 &
#890
b100 4
b100 %
b100 +
b10 .
b1 -
b101 /
b100 &
#900
b1000 4
b1000 3
b10 2
b10 #
b1 3
b1 $
b1 4
b1 %
b1 +
b1 *
b10 )
b0 .
b10 -
b11 ,
b1 /
b1 &
#910
b10 4
b10 %
b10 +
b11 -
b10 ,
b10 /
b10 &
#920
b100 4
b100 %
b100 +
b1 .
b10 -
b11 /
#930
b1000 4
b10 3
b10 $
b1 4
b1 %
b1 +
b10 *
b0 .
b11 -
b10 /
#940
b10 4
b10 %
b10 +
b100 -
b1 ,
#950
b100 4
b100 %
b100 +
b1 .
b11 -
#960
b1000 4
b100 3
b100 $
b1 4
b1 %
b1 +
b100 *
b10 -
b10 ,
b11 /
#970
b10 4
b10 %
b10 +
b11 -
b1 ,
b10 /
#980
b100 4
b100 %
b100 +
b10 .
b10 -
b110 /
b100 &
#990
b1000 4
b1000 3
b100 2
b100 #
b1 3
b1 $
b1 4
b1 %
b1 +
b1 *
b100 )
b1 .
b1 -
b11 ,
b1 /
b1 &
#1000
b10 4
b10 %
b10 +
b10 -
b10 ,
b11 /
b10 &
#1010
b100 4
b100 %
b100 +
b10 .
b1 -
b101 /
b100 &
#1020
b1000 4
b10 3
b10 $
b1 4
b1 %
b1 +
b10 *
b1 .
b10 -
b11 /
b10 &
#1030
b10 4
b10 %
b10 +
b11 -
b1 ,
b10 /
#1040
b100 4
b100 %
b100 +
b10 .
b10 -
b110 /
b100 &
#1050
b1000 4
b100 3
b100 $
b1 4
b1 %
b1 +
b100 *
b1 -
b10 ,
b101 /
#1060
b10 4
b10 %
b10 +
b10 -
b1 ,
b110 /
#1070
b100 4
b100 %
b100 +
b11 .
b1 -
b100 /
#1080
b1000 4
b1000 3
b1000 2
b10 1
b10 "
b1 2
b1 #
b1 3
b1 $
b1 4
b1 %
b1 +
b1 *
b1 )
b10 (
b0 .
b10 -
b11 ,
b1 /
b1 &
#1090
b10 4
b10 %
b10 +
b11 -
b10 ,
b10 /
b10 &
#1100
b100 4
b100 %
b100 +
b1 .
b10 -
b11 /
#1110
b1000 4
b10 3
b10 $
b1 4
b1 %
b1 +
b10 *
b0 .
b11 -
b10 /
#1120
b10 4
b10 %
b10 +
b100 -
b1 ,
#1130
b100 4
b100 %
b100 +
b1 .
b11 -
#1140
b1000 4
b100 3
b100 $
b1 4
b1 %
b1 +
b100 *
b10 -
b10 ,
b11 /
#1150
b10 4
b10 %
b10 +
b11 -
b1 ,
b10 /
#1160
b100 4
b100 %
b100 +
b10 .
b10 -
b110 /
b100 &
#1170
b1000 4
b1000 3
b10 2
b10 #
b1 3
b1 $
b1 4
b1 %
b1 +
b1 *
b10 )
b0 .
b11 -
b10 ,
b10 /
b10 &
#1180
b10 4
b10 %
b10 +
b100 -
b1 ,
#1190
b100 4
b100 %
b100 +
b1 .
b11 -
#1200
b1000 4
b10 3
b10 $
b1 4
b1 %
b1 +
b10 *
b0 .
b100 -
#1210
b10 4
b10 %
b10 +
b101 -
b0 ,
#1220
b100 4
b100 %
b100 +
b1 .
b100 -
#1230
b1000 4
b100 3
b100 $
b1 4
b1 %
b1 +
b100 *
b11 -
b1 ,
#1240
b10 4
b10 %
b10 +
b100 -
b0 ,
#1250
b100 4
b100 %
b100 +
b10 .
b11 -
#1260
b1000 4
b1000 3
b100 2
b100 #
b1 3
b1 $
b1 4
b1 %
b1 +
b1 *
b100 )
b1 .
b10 -
b10 ,
b11 /
#1270
b10 4
b10 %
b10 +
b11 -
b1 ,
b10 /
#1280
b100 4
b100 %
b100 +
b10 .
b10 -
b110 /
b100 &
#1290
b1000 4
b10 3
b10 $
b1 4
b1 %
b1 +
b10 *
b1 .
b11 -
b10 /
b10 &
#1300
b10 4
b10 %
b10 +
b100 -
b0 ,
#1310
b100 4
b100 %
b100 +
b10 .
b11 -
#1320
b1000 4
b100 3
b100 $
b1 4
b1 %
b1 +
b100 *
b10 -
b1 ,
b110 /
b100 &
#1330
b10 4
b10 %
b10 +
b11 -
b0 ,
b10 /
b10 &
#1340
b100 4
b100 %
b100 +
b11 .
b10 -
b100 /
b100 &
#1350
b1000 4
b1000 3
b1000 2
b100 1
b100 "
b1 2
b1 #
b1 3
b1 $
b1 4
b1 %
b1 +
b1 *
b1 )
b100 (
b1 .
b1 -
b11 ,
b1 /
b1 &
#1360
b10 4
b10 %
b10 +
b10 -
b10 ,
b11 /
b10 &
#1370
b100 4
b100 %
b100 +
b10 .
b1 -
b101 /
b100 &
#1380
b1000 4
b10 3
b10 $
b1 4
b1 %
b1 +
b10 *
b1 .
b10 -
b11 /
b10 &
#1390
b10 4
b10 %
b10 +
b11 -
b1 ,
b10 /
#1400
b100 4
b100 %
b100 +
b10 .
b10 -
b110 /
b100 &
#1410
b1000 4
b100 3
b100 $
b1 4
b1 %
b1 +
b100 *
b1 -
b10 ,
b101 /
#1420
b10 4
b10 %
b10 +
b10 -
b1 ,
b110 /
#1430
b100 4
b100 %
b100 +
b11 .
b1 -
b100 /
#1440
b1000 4
b1000 3
b10 2
b10 #
b1 3
b1 $
b1 4
b1 %
b1 +
b1 *
b10 )
b1 .
b10 -
b10 ,
b11 /
b10 &
#1450
b10 4
b10 %
b10 +
b11 -
b1 ,
b10 /
#1460
b100 4
b100 %
b100 +
b10 .
b10 -
b110 /
b100 &
#1470
b1000 4
b10 3
b10 $
b1 4
b1 %
b1 +
b10 *
b1 .
b11 -
b10 /
b10 &
#1480
b10 4
b10 %
b10 +
b100 -
b0 ,
#1490
b100 4
b100 %
b100 +
b10 .
b11 -
#1500
b1000 4
b100 3
b100 $
b1 4
b1 %
b1 +
b100 *
b10 -
b1 ,
b110 /
b100 &
#1510
b10 4
b10 %
b10 +
b11 -
b0 ,
b10 /
b10 &
#1520
b100 4
b100 %
b100 +
b11 .
b10 -
b100 /
b100 &
#1530
b1000 4
b1000 3
b100 2
b100 #
b1 3
b1 $
b1 4
b1 %
b1 +
b1 *
b100 )
b10 .
b1 -
b10 ,
b101 /
#1540
b10 4
b10 %
b10 +
b10 -
b1 ,
b110 /
#1550
b100 4
b100 %
b100 +
b11 .
b1 -
b100 /
#1560
b1000 4
b10 3
b10 $
b1 4
b1 %
b1 +
b10 *
b10 .
b10 -
b110 /
#1570
b10 4
b10 %
b10 +
b11 -
b0 ,
b10 /
b10 &
#1580
b100 4
b100 %
b100 +
b11 .
b10 -
b100 /
b100 &
#1590
b1000 4
b100 3
b100 $
b1 4
b1 %
b1 +
b100 *
b1 -
b1 ,
#1600
b10 4
b10 %
b10 +
b10 -
b0 ,
#1610
b100 4
b100 %
b100 +
b100 .
b1 -
#1620
b1000 4
b1000 3
b1000 2
b1000 1
b100 0
b100 !
b1 1
b1 "
b1 2
b1 #
b1 3
b1 $
b1 4
b1 %
b1 +
b1 *
b1 )
b1 (
b100 '
b1 .
b0 -
b100 ,
b1 /
b1 &
#1630
b10 4
b10 %
b10 +
b1 -
b11 ,
#1640
b100 4
b100 %
b100 +
b10 .
b0 -
#1650
b1000 4
b10 3
b10 $
b1 4
b1 %
b1 +
b10 *
b1 .
b1 -
#1660
b10 4
b10 %
b10 +
b10 -
b10 ,
b11 /
b10 &
#1670
b100 4
b100 %
b100 +
b10 .
b1 -
b101 /
b100 &
#1680
b1000 4
b100 3
b100 $
b1 4
b1 %
b1 +
b100 *
b0 -
b11 ,
b1 /
b1 &
#1690
b10 4
b10 %
b10 +
b1 -
b10 ,
b101 /
b100 &
#1700
b100 4
b100 %
b100 +
b11 .
b0 -
b100 /
#1710
b1000 4
b1000 3
b10 2
b10 #
b1 3
b1 $
b1 4
b1 %
b1 +
b1 *
b10 )
b1 .
b1 -
b11 ,
b1 /
b1 &
#1720
b10 4
b10 %
b10 +
b10 -
b10 ,
b11 /
b10 &
#1730
b100 4
b100 %
b100 +
b10 .
b1 -
b101 /
b100 &
#1740
b1000 4
b10 3
b10 $
b1 4
b1 %
b1 +
b10 *
b1 .
b10 -
b11 /
b10 &
#1750
b10 4
b10 %
b10 +
b11 -
b1 ,
b10 /
#1760
b100 4
b100 %
b100 +
b10 .
b10 -
b110 /
b100 &
#1770
b1000 4
b100 3
b100 $
b1 4
b1 %
b1 +
b100 *
b1 -
b10 ,
b101 /
#1780
b10 4
b10 %
b10 +
b10 -
b1 ,
b110 /
#1790
b100 4
b100 %
b100 +
b11 .
b1 -
b100 /
#1800
b1000 4
b1000 3
b100 2
b100 #
b1 3
b1 $
b1 4
b1 %
b1 +
b1 *
b100 )
b10 .
b0 -
b11 ,
b1 /
b1 &
#1810
b10 4
b10 %
b10 +
b1 -
b10 ,
b101 /
b100 &
#1820
b100 4
b100 %
b100 +
b11 .
b0 -
b100 /
#1830
b1000 4
b10 3
b10 $
b1 4
b1 %
b1 +
b10 *
b10 .
b1 -
b101 /
#1840
b10 4
b10 %
b10 +
b10 -
b1 ,
b110 /
#1850
b100 4
b100 %
b100 +
b11 .
b1 -
b100 /
#1860
b1000 4
b100 3
b100 $
b1 4
b1 %
b1 +
b100 *
b0 -
b10 ,
#1870
b10 4
b10 %
b10 +
b1 -
b1 ,
#1880
b100 4
b100 %
b100 +
b100 .
b0 -
#1890
b1000 4
b1000 3
b1000 2
b10 1
b10 "
b1 2
b1 #
b1 3
b1 $
b1 4
b1 %
b1 +
b1 *
b1 )
b10 (
b1 .
b1 -
b11 ,
b1 /
b1 &
#1900
b10 4
b10 %
b10 +
b10 -
b10 ,
b11 /
b10 &
#1910
b100 4
b100 %
b100 +
b10 .
b1 -
b101 /
b100 &
#1920
b1000 4
b10 3
b10 $
b1 4
b1 %
b1 +
b10 *
b1 .
b10 -
b11 /
b10 &
#1930
b10 4
b10 %
b10 +
b11 -
b1 ,
b10 /
#1940
b100 4
b100 %
b100 +
b10 .
b10 -
b110 /
b100 &
#1950
b1000 4
b100 3
b100 $
b1 4
b1 %
b1 +
b100 *
b1 -
b10 ,
b101 /
#1960
b10 4
b10 %
b10 +
b10 -
b1 ,
b110 /
#1970
b100 4
b100 %
b100 +
b11 .
b1 -
b100 /
#1980
b1000 4
b1000 3
b10 2
b10 #
b1 3
b1 $
b1 4
b1 %
b1 +
b1 *
b10 )
b1 .
b10 -
b10 ,
b11 /
b10 &
#1990
b10 4
b10 %
b10 +
b11 -
b1 ,
b10 /
#2000
b100 4
b100 %
b100 +
b10 .
b10 -
b110 /
b100 &
#2010
b1000 4
b10 3
b10 $
b1 4
b1 %
b1 +
b10 *
b1 .
b11 -
b10 /
b10 &
#2020
b10 4
b10 %
b10 +
b100 -
b0 ,
#2030
b100 4
b100 %
b100 +
b10 .
b11 -
#2040
b1000 4
b100 3
b100 $
b1 4
b1 %
b1 +
b100 *
b10 -
b1 ,
b110 /
b100 &
#2050
b10 4
b10 %
b10 +
b11 -
b0 ,
b10 /
b10 &
#2060
b100 4
b100 %
b100 +
b11 .
b10 -
b100 /
b100 &
#2070
b1000 4
b1000 3
b100 2
b100 #
b1 3
b1 $
b1 4
b1 %
b1 +
b1 *
b100 )
b10 .
b1 -
b10 ,
b101 /
#2080
b10 4
b10 %
b10 +
b10 -
b1 ,
b110 /
#2090
b100 4
b100 %
b100 +
b11 .
b1 -
b100 /
#2100
b1000 4
b10 3
b10 $
b1 4
b1 %
b1 +
b10 *
b10 .
b10 -
b110 /
#2110
b10 4
b10 %
b10 +
b11 -
b0 ,
b10 /
b10 &
#2120
b100 4
b100 %
b100 +
b11 .
b10 -
b100 /
b100 &
#2130
b1000 4
b100 3
b100 $
b1 4
b1 %
b1 +
b100 *
b1 -
b1 ,
#2140
b10 4
b10 %
b10 +
b10 -
b0 ,
#2150
b100 4
b100 %
b100 +
b100 .
b1 -
#2160
b1000 4
b1000 3
b1000 2
b100 1
b100 "
b1 2
b1 #
b1 3
b1 $
b1 4
b1 %
b1 +
b1 *
b1 )
b100 (
b10 .
b0 -
b11 ,
b1 /
b1 &
#2170
b10 4
b10 %
b10 +
b1 -
b10 ,
b101 /
b100 &
#2180
b100 4
b100 %
b100 +
b11 .
b0 -
b100 /
#2190
b1000 4
b10 3
b10 $
b1 4
b1 %
b1 +
b10 *
b10 .
b1 -
b101 /
#2200
b10 4
b10 %
b10 +
b10 -
b1 ,
b110 /
#2210
b100 4
b100 %
b100 +
b11 .
b1 -
b100 /
#2220
b1000 4
b100 3
b100 $
b1 4
b1 %
b1 +
b100 *
b0 -
b10 ,
#2230
b10 4
b10 %
b10 +
b1 -
b1 ,
#2240
b100 4
b100 %
b100 +
b100 .
b0 -
#2250
b1000 4
b1000 3
b10 2
b10 #
b1 3
b1 $
b1 4
b1 %
b1 +
b1 *
b10 )
b10 .
b1 -
b10 ,
b101 /
#2260
b10 4
b10 %
b10 +
b10 -
b1 ,
b110 /
#2270
b100 4
b100 %
b100 +
b11 .
b1 -
b100 /
#2280
b1000 4
b10 3
b10 $
b1 4
b1 %
b1 +
b10 *
b10 .
b10 -
b110 /
#2290
b10 4
b10 %
b10 +
b11 -
b0 ,
b10 /
b10 &
#2300
b100 4
b100 %
b100 +
b11 .
b10 -
b100 /
b100 &
#2310
b1000 4
b100 3
b100 $
b1 4
b1 %
b1 +
b100 *
b1 -
b1 ,
#2320
b10 4
b10 %
b10 +
b10 -
b0 ,
#2330
b100 4
b100 %
b100 +
b100 .
b1 -
#2340
b1000 4
b1000 3
b100 2
b100 #
b1 3
b1 $
b1 4
b1 %
b1 +
b1 *
b100 )
b11 .
b0 -
b10 ,
#2350
b10 4
b10 %
b10 +
b1 -
b1 ,
#2360
b100 4
b100 %
b100 +
b100 .
b0 -
#2370
b1000 4
b10 3
b10 $
b1 4
b1 %
b1 +
b10 *
b11 .
b1 -
#2380
b10 4
b10 %
b10 +
b10 -
b0 ,
#2390
b100 4
b100 %
b100 +
b100 .
b1 -
#2400
b1000 4
b100 3
b100 $
b1 4
b1 %
b1 +
b100 *
b0 -
b1 ,
#2410
b10 4
b10 %
b10 +
b1 -
b0 ,
#2420
b100 4
b100 %
b100 +
b101 .
b0 -
#2430
b1000 4
b1000 3
b1000 2
b1000 1
b1000 0
